mirage_api/__init__.py
mirage_api/resources/__init__.py
mirage_api/resources/data.py
mirage_api/resources/task.py
mirage_api-2.0.0.dist-info/licenses/AUTHORS
mirage_api-2.0.0.dist-info/licenses/LICENSE
mirage_api-2.0.0.dist-info/METADATA
mirage_api-2.0.0.dist-info/WHEEL
mirage_api-2.0.0.dist-info/top_level.txt
mirage_api-2.0.0.dist-info/RECORD
