Metadata-Version: 2.4
Name: mirage-api
Version: 2.0.0
Summary: Mirage API Python wrapper.
Home-page: https://github.com/mirage-ai-com/python-mirage-api
Author: Valerian Saliou
Author-email: valerian@valeriansaliou.name
License: MIT - http://opensource.org/licenses/mit-license.php
Classifier: Environment :: Web Environment
Classifier: Intended Audience :: Developers
Classifier: Natural Language :: English
Classifier: Programming Language :: Python
License-File: LICENSE
License-File: AUTHORS
Dynamic: author
Dynamic: author-email
Dynamic: classifier
Dynamic: description
Dynamic: description-content-type
Dynamic: home-page
Dynamic: license
Dynamic: license-file
Dynamic: summary
